BingChatAPI/BingChatAPI.py
BingChatAPI/__init__.py
bingchatAPI-0.0.1.dist-info/METADATA
bingchatAPI-0.0.1.dist-info/WHEEL
bingchatAPI-0.0.1.dist-info/top_level.txt
bingchatAPI-0.0.1.dist-info/RECORD
