Metadata-Version: 2.1
Name: bingchatAPI
Version: 0.0.1
Summary: Unofficial BingChat API
Home-page: UNKNOWN
Author: DarkMatter-999
Author-email: <darkmatter999official@gmail.com>
License: UNKNOWN
Keywords: chatgpt,gpt4,bingchat,bing,openai,api,python,lachine learning,natural language processing
Platform: UNKNOWN
Classifier: Development Status :: 1 - Planning
Classifier: Intended Audience :: Developers
Classifier: Programming Language :: Python :: 3
Classifier: Operating System :: Unix
Classifier: Operating System :: MacOS :: MacOS X
Classifier: Operating System :: Microsoft :: Windows
Requires-Dist: aioconsole
Requires-Dist: autopep8
Requires-Dist: certifi
Requires-Dist: charset-normalizer
Requires-Dist: idna
Requires-Dist: pycodestyle
Requires-Dist: python-dotenv
Requires-Dist: requests
Requires-Dist: tomli
Requires-Dist: urllib3
Requires-Dist: websockets
